[
  {
    "id": 1,
    "name": "first",
    "full_name": "user/first",
    "fork": false,
    "html_url": "https://github.com/user/first",
    "language": null
  },
  {
    "id": 2,
    "name": "second",
    "full_name": "user/second",
    "fork": false,
    "html_url": "https://github.com/user/second",
    "language": null
  },
  {
    "id": 3,
    "name": "third",
    "full_name": "user/third",
    "fork": true,
    "html_url": "https://github.com/user/third",
    "language": null
  },
  {
    "id": 3,
    "name": "third",
    "full_name": "user/third",
    "fork": true,
    "html_url": "https://github.com/user/third",
    "language": null
  }
]
